README.md
setup.cfg
setup.py
climadjust/__init__.py
climadjust/client.py
climadjust/urls.py
climadjust.egg-info/PKG-INFO
climadjust.egg-info/SOURCES.txt
climadjust.egg-info/dependency_links.txt
climadjust.egg-info/requires.txt
climadjust.egg-info/top_level.txt
climadjust/DTOs/__init__.py
climadjust/DTOs/dataset.py
climadjust/DTOs/experiment.py
climadjust/DTOs/pagination.py
climadjust/clientMethods/__init__.py
climadjust/clientMethods/dataset_mixin.py
climadjust/clientMethods/experiment_mixin.py