Metadata-Version: 2.1
Name: climadjust
Version: 1.0
Summary: Python client for Climadjust API
Home-page: UNKNOWN
Author: Predictia
License: MIT
Platform: GNU/Linux
